nunininu_check_os_ver-0.4.0.dist-info/METADATA
nunininu_check_os_ver-0.4.0.dist-info/WHEEL
nunininu_check_os_ver-0.4.0.dist-info/entry_points.txt
nunininu_check_os_ver/__init__.py
nunininu_check_os_ver/hi.py
nunininu_check_os_ver/osver.py
nunininu_check_os_ver-0.4.0.dist-info/RECORD
