Metadata-Version: 2.1
Name: nunininu-check-os-ver
Version: 0.4.0
Summary: Default template for PDM package
Author-Email: nunininu <sgcho0907@gmail.com>
License: MIT
Project-URL: Homepage, https://github.com/nunininu/nunininu-check-os-ver
Project-URL: Issues, https://github.com/nunininu/nunininu-check-os-ver/issues
Requires-Python: >=3.10
Requires-Dist: stundrg-check-os-ver>=0.2.3
Requires-Dist: cho-check-os-ver>=0.2.3
Requires-Dist: lucas-check-os-ver>=0.2.1
Requires-Dist: check-os-ver>=0.2.1
Requires-Dist: seo-check-os-version>=0.2.0
Requires-Dist: jacob-os-version-check>=0.2.4
Requires-Dist: hj-check-os-version>=0.2.1
